LICENSE.md
MANIFEST.in
README.md
setup.py
Watson.egg-info/PKG-INFO
Watson.egg-info/SOURCES.txt
Watson.egg-info/dependency_links.txt
Watson.egg-info/requires.txt
Watson.egg-info/top_level.txt
watson/__init__.py
watson/chatbot.py
watson/firebot.py
watson/gbot.py
watson/grammar.py
watson/shellbot.py
watson/stateful.py
watson/modules/__init__.py
watson/modules/adventuregame.py
watson/modules/articles.py
watson/modules/bangbang.py
watson/modules/chatmodule.py
watson/modules/help.py
watson/modules/images.py
watson/modules/mathchallenge.py
watson/modules/quips.py
watson/modules/rottentomatoes.py
watson/modules/stop.py
watson/tests/__init__.py
watson/tests/commandtest.py