Metadata-Version: 1.0
Name: Watson
Version: 0.1.05
Summary: The Chatbot that won America's hearts in the 80's is back! And this time, he means business!
Home-page: https://github.com/Babbaco/Watson
Author: Babbaco
Author-email: UNKNOWN
License: LICENSE.txt
Platform: UNKNOWN
